CHANGELOG.md
fireworks/__init__.py
fireworks/_const.py
fireworks/_literals.py
fireworks/_logger.py
fireworks/_util.py
fireworks/batch_inference_job/__init__.py
fireworks/batch_inference_job/batch_inference_job.py
fireworks/client/__init__.py
fireworks/client/_constants.py
fireworks/client/_version.py
fireworks/client/api.py
fireworks/client/api_client.py
fireworks/client/api_client_v2.py
fireworks/client/audio.py
fireworks/client/audio_api.py
fireworks/client/base_completion.py
fireworks/client/chat.py
fireworks/client/chat_completion.py
fireworks/client/completion.py
fireworks/client/embedding.py
fireworks/client/error.py
fireworks/client/gateway.py
fireworks/client/image.py
fireworks/client/image_api.py
fireworks/client/log.py
fireworks/client/model.py
fireworks/client/rerank.py
fireworks/client/sagemaker.py
fireworks/control_plane/generated/protos/__init__.py
fireworks/control_plane/generated/protos/buf/__init__.py
fireworks/control_plane/generated/protos/buf/validate/__init__.py
fireworks/control_plane/generated/protos/gateway/__init__.py
fireworks/control_plane/generated/protos/google/__init__.py
fireworks/control_plane/generated/protos/google/api/__init__.py
fireworks/control_plane/generated/protos/google/longrunning/__init__.py
fireworks/control_plane/generated/protos/google/rpc/__init__.py
fireworks/control_plane/generated/protos/google/type/__init__.py
fireworks/control_plane/generated/protos_grpcio/__init__.py
fireworks/control_plane/generated/protos_grpcio/buf/validate/validate_pb2.py
fireworks/control_plane/generated/protos_grpcio/buf/validate/validate_pb2.pyi
fireworks/control_plane/generated/protos_grpcio/buf/validate/validate_pb2_grpc.py
fireworks/control_plane/generated/protos_grpcio/gateway/__init__.py
fireworks/control_plane/generated/protos_grpcio/gateway/abuse_rule_pb2.py
fireworks/control_plane/generated/protos_grpcio/gateway/abuse_rule_pb2.pyi
fireworks/control_plane/generated/protos_grpcio/gateway/abuse_rule_pb2_grpc.py
fireworks_ai-0.19.18.dist-info/METADATA
fireworks_ai-0.19.18.dist-info/WHEEL
fireworks_ai-0.19.18.dist-info/entry_points.txt
fireworks_ai-0.19.18.dist-info/licenses/LICENSE
fireworks_ai-0.19.18.dist-info/RECORD
