Metadata-Version: 2.1
Name: fireworks-ai
Version: 0.19.18
Summary: Python client library for the Fireworks AI Platform
Author-Email: Fireworks AI <info@fireworks.ai>
License: MIT
Classifier: Programming Language :: Python :: 3
Classifier: License :: OSI Approved :: MIT License
Classifier: Operating System :: OS Independent
Classifier: Topic :: Scientific/Engineering :: Artificial Intelligence
Classifier: Development Status :: 3 - Alpha
Project-URL: Homepage, https://fireworks.ai
Requires-Python: >=3.10
Requires-Dist: httpx
Requires-Dist: httpx-ws
Requires-Dist: httpx-sse
Requires-Dist: pydantic
Requires-Dist: Pillow
Requires-Dist: openai
Requires-Dist: typing_extensions
Requires-Dist: mmh3>=4.1.0
Requires-Dist: betterproto-fw[compiler]>=2.0.3
Requires-Dist: asyncstdlib-fw>=3.13.2
Requires-Dist: grpcio>=1.71.0
Requires-Dist: protobuf==5.29.3
Requires-Dist: rich>=14.0.0
Requires-Dist: reward-kit>=0.3.1
Requires-Dist: toml>=0.10.2
Requires-Dist: aiohttp[speedups]>=3.12.11
Requires-Dist: attrs==23.2.0
Requires-Dist: googleapis-common-protos>=1.60.0
Provides-Extra: flumina
Requires-Dist: fastapi; extra == "flumina"
Requires-Dist: tabulate; extra == "flumina"
Requires-Dist: prance; extra == "flumina"
Requires-Dist: openapi-spec-validator; extra == "flumina"
Requires-Dist: gitignore-parser; extra == "flumina"
Requires-Dist: safetensors; extra == "flumina"
Requires-Dist: tqdm; extra == "flumina"
Requires-Dist: torch; extra == "flumina"
